{
  "annotations": {
    "list": [
      {
        "builtIn": 1,
        "datasource": {
          "type": "grafana",
          "uid": "-- Grafana --"
        },
        "enable": true,
        "hide": true,
        "iconColor": "rgba(0, 211, 255, 1)",
        "name": "Annotations & Alerts",
        "type": "dashboard"
      }
    ]
  },
  "editable": true,
  "fiscalYearStartMonth": 0,
  "graphTooltip": 1,
  "id": 2,
  "links": [],
  "panels": [
    {
      "collapsed": false,
      "gridPos": {
        "h": 1,
        "w": 24,
        "x": 0,
        "y": 0
      },
      "id": 8,
      "panels": [],
      "title": "Main",
      "type": "row"
    },
    {
      "datasource": {
        "type": "prometheus",
        "uid": "prometheus"
      },
      "fieldConfig": {
        "defaults": {
          "color": {
            "mode": "palette-classic"
          },
          "custom": {
            "axisBorderShow": false,
            "axisCenteredZero": false,
            "axisColorMode": "text",
            "axisLabel": "",
            "axisPlacement": "auto",
            "barAlignment": 0,
            "barWidthFactor": 0.6,
            "drawStyle": "line",
            "fillOpacity": 10,
            "gradientMode": "opacity",
            "hideFrom": {
              "legend": false,
              "tooltip": false,
              "viz": false
            },
            "insertNulls": false,
            "lineInterpolation": "linear",
            "lineWidth": 2,
            "pointSize": 5,
            "scaleDistribution": {
              "type": "linear"
            },
            "showPoints": "never",
            "spanNulls": false,
            "stacking": {
              "group": "A",
              "mode": "none"
            },
            "thresholdsStyle": {
              "mode": "off"
            }
          },
          "mappings": [],
          "thresholds": {
            "mode": "absolute",
            "steps": [
              {
                "color": "green",
                "value": 0
              },
              {
                "color": "red",
                "value": 50
              }
            ]
          },
          "unit": "short"
        },
        "overrides": []
      },
      "gridPos": {
        "h": 10,
        "w": 8,
        "x": 0,
        "y": 1
      },
      "id": 1,
      "options": {
        "legend": {
          "calcs": [],
          "displayMode": "table",
          "placement": "right",
          "showLegend": true,
          "width": 320
        },
        "tooltip": {
          "hideZeros": false,
          "mode": "multi",
          "sort": "none"
        }
      },
      "pluginVersion": "12.1.1",
      "targets": [
        {
          "datasource": {
            "type": "prometheus",
            "uid": "prometheus"
          },
          "editorMode": "code",
          "expr": "sum by (method, route, status) (rate(app_http_requests_total{status=~\"2..\"}[5m])) * 60",
          "instant": false,
          "legendFormat": "{{method}}.{{route}}.{{status}}",
          "range": true,
          "refId": "A"
        }
      ],
      "title": "2XX OK",
      "type": "timeseries"
    },
    {
      "datasource": {
        "type": "prometheus",
        "uid": "prometheus"
      },
      "fieldConfig": {
        "defaults": {
          "color": {
            "mode": "palette-classic"
          },
          "custom": {
            "axisBorderShow": false,
            "axisCenteredZero": false,
            "axisColorMode": "text",
            "axisLabel": "",
            "axisPlacement": "auto",
            "barAlignment": 0,
            "barWidthFactor": 0.6,
            "drawStyle": "line",
            "fillOpacity": 10,
            "gradientMode": "opacity",
            "hideFrom": {
              "legend": false,
              "tooltip": false,
              "viz": false
            },
            "insertNulls": false,
            "lineInterpolation": "linear",
            "lineWidth": 2,
            "pointSize": 5,
            "scaleDistribution": {
              "type": "linear"
            },
            "showPoints": "never",
            "spanNulls": false,
            "stacking": {
              "group": "A",
              "mode": "none"
            },
            "thresholdsStyle": {
              "mode": "off"
            }
          },
          "mappings": [],
          "thresholds": {
            "mode": "absolute",
            "steps": [
              {
                "color": "green",
                "value": 0
              },
              {
                "color": "red",
                "value": 10
              }
            ]
          },
          "unit": "short"
        },
        "overrides": []
      },
      "gridPos": {
        "h": 10,
        "w": 8,
        "x": 8,
        "y": 1
      },
      "id": 6,
      "options": {
        "legend": {
          "calcs": [],
          "displayMode": "table",
          "placement": "right",
          "showLegend": true,
          "width": 320
        },
        "tooltip": {
          "hideZeros": false,
          "mode": "multi",
          "sort": "none"
        }
      },
      "pluginVersion": "12.1.1",
      "targets": [
        {
          "datasource": {
            "type": "prometheus",
            "uid": "prometheus"
          },
          "editorMode": "code",
          "expr": "sum by (method, route, status) (rate(app_http_requests_total{status=~\"4..\"}[5m])) * 60",
          "instant": false,
          "legendFormat": "{{method}}.{{route}}.{{status}}",
          "range": true,
          "refId": "A"
        }
      ],
      "title": "4XX ERRORS",
      "type": "timeseries"
    },
    {
      "datasource": {
        "type": "prometheus",
        "uid": "prometheus"
      },
      "fieldConfig": {
        "defaults": {
          "color": {
            "mode": "palette-classic"
          },
          "custom": {
            "axisBorderShow": false,
            "axisCenteredZero": false,
            "axisColorMode": "text",
            "axisLabel": "",
            "axisPlacement": "auto",
            "barAlignment": 0,
            "barWidthFactor": 0.6,
            "drawStyle": "line",
            "fillOpacity": 10,
            "gradientMode": "opacity",
            "hideFrom": {
              "legend": false,
              "tooltip": false,
              "viz": false
            },
            "insertNulls": false,
            "lineInterpolation": "linear",
            "lineWidth": 2,
            "pointSize": 5,
            "scaleDistribution": {
              "type": "linear"
            },
            "showPoints": "never",
            "spanNulls": false,
            "stacking": {
              "group": "A",
              "mode": "none"
            },
            "thresholdsStyle": {
              "mode": "off"
            }
          },
          "mappings": [],
          "thresholds": {
            "mode": "absolute",
            "steps": [
              {
                "color": "green",
                "value": 0
              },
              {
                "color": "red",
                "value": 10
              }
            ]
          },
          "unit": "short"
        },
        "overrides": []
      },
      "gridPos": {
        "h": 10,
        "w": 8,
        "x": 16,
        "y": 1
      },
      "id": 7,
      "options": {
        "legend": {
          "calcs": [],
          "displayMode": "table",
          "placement": "right",
          "showLegend": true,
          "width": 320
        },
        "tooltip": {
          "hideZeros": false,
          "mode": "multi",
          "sort": "none"
        }
      },
      "pluginVersion": "12.1.1",
      "targets": [
        {
          "datasource": {
            "type": "prometheus",
            "uid": "prometheus"
          },
          "editorMode": "code",
          "expr": "sum by (method, route, status) (rate(app_http_requests_total{status=~\"5..\"}[5m])) * 60",
          "instant": false,
          "legendFormat": "{{method}}.{{route}}.{{status}}",
          "range": true,
          "refId": "A"
        }
      ],
      "title": "5XX ERRORS",
      "type": "timeseries"
    },
    {
      "datasource": {
        "type": "prometheus",
        "uid": "prometheus"
      },
      "fieldConfig": {
        "defaults": {
          "color": {
            "mode": "palette-classic"
          },
          "custom": {
            "axisBorderShow": false,
            "axisCenteredZero": false,
            "axisColorMode": "text",
            "axisLabel": "",
            "axisPlacement": "auto",
            "barAlignment": 0,
            "barWidthFactor": 0.6,
            "drawStyle": "line",
            "fillOpacity": 10,
            "gradientMode": "opacity",
            "hideFrom": {
              "legend": false,
              "tooltip": false,
              "viz": false
            },
            "insertNulls": false,
            "lineInterpolation": "linear",
            "lineWidth": 2,
            "pointSize": 5,
            "scaleDistribution": {
              "type": "linear"
            },
            "showPoints": "never",
            "spanNulls": false,
            "stacking": {
              "group": "A",
              "mode": "none"
            },
            "thresholdsStyle": {
              "mode": "off"
            }
          },
          "mappings": [],
          "thresholds": {
            "mode": "absolute",
            "steps": [
              {
                "color": "green",
                "value": 0
              },
              {
                "color": "red",
                "value": 0.5
              }
            ]
          },
          "unit": "s"
        },
        "overrides": []
      },
      "gridPos": {
        "h": 10,
        "w": 24,
        "x": 0,
        "y": 11
      },
      "id": 2,
      "options": {
        "legend": {
          "calcs": [],
          "displayMode": "table",
          "placement": "right",
          "showLegend": true,
          "width": 320
        },
        "tooltip": {
          "hideZeros": false,
          "mode": "multi",
          "sort": "none"
        }
      },
      "pluginVersion": "12.1.1",
      "targets": [
        {
          "datasource": {
            "type": "prometheus",
            "uid": "prometheus"
          },
          "editorMode": "code",
          "expr": "histogram_quantile(0.${percentile}, sum by (le, method, route, status) (rate(app_http_request_duration_seconds_bucket[5m])))",
          "instant": false,
          "legendFormat": "{{method}}.{{route}}.{{status}}",
          "range": true,
          "refId": "A"
        }
      ],
      "title": "P${percentile} Latency",
      "type": "timeseries"
    },
    {
      "collapsed": true,
      "gridPos": {
        "h": 1,
        "w": 24,
        "x": 0,
        "y": 21
      },
      "id": 9,
      "panels": [
        {
          "datasource": {
            "type": "prometheus",
            "uid": "prometheus"
          },
          "fieldConfig": {
            "defaults": {
              "color": {
                "mode": "palette-classic"
              },
              "custom": {
                "axisBorderShow": false,
                "axisCenteredZero": false,
                "axisColorMode": "text",
                "axisLabel": "",
                "axisPlacement": "auto",
                "barAlignment": 0,
                "barWidthFactor": 0.6,
                "drawStyle": "line",
                "fillOpacity": 10,
                "gradientMode": "opacity",
                "hideFrom": {
                  "legend": false,
                  "tooltip": false,
                  "viz": false
                },
                "insertNulls": false,
                "lineInterpolation": "linear",
                "lineWidth": 2,
                "pointSize": 5,
                "scaleDistribution": {
                  "type": "linear"
                },
                "showPoints": "never",
                "spanNulls": false,
                "stacking": {
                  "group": "A",
                  "mode": "none"
                },
                "thresholdsStyle": {
                  "mode": "off"
                }
              },
              "mappings": [],
              "thresholds": {
                "mode": "absolute",
                "steps": [
                  {
                    "color": "green",
                    "value": 0
                  },
                  {
                    "color": "red",
                    "value": 80
                  }
                ]
              },
              "unit": "percentunit"
            },
            "overrides": []
          },
          "gridPos": {
            "h": 9,
            "w": 12,
            "x": 0,
            "y": 22
          },
          "id": 3,
          "options": {
            "legend": {
              "calcs": [],
              "displayMode": "table",
              "placement": "right",
              "showLegend": true,
              "width": 220
            },
            "tooltip": {
              "hideZeros": false,
              "mode": "multi",
              "sort": "none"
            }
          },
          "pluginVersion": "12.1.1",
          "targets": [
            {
              "datasource": {
                "type": "prometheus",
                "uid": "prometheus"
              },
              "editorMode": "code",
              "expr": "100 * (1 - avg by (instance) (rate(node_cpu_seconds_total{mode=\"idle\"}[5m])))",
              "instant": false,
              "legendFormat": "{{instance}}",
              "range": true,
              "refId": "A"
            }
          ],
          "title": "CPU Usage",
          "type": "timeseries"
        },
        {
          "datasource": {
            "type": "prometheus",
            "uid": "prometheus"
          },
          "fieldConfig": {
            "defaults": {
              "color": {
                "mode": "palette-classic"
              },
              "custom": {
                "axisBorderShow": false,
                "axisCenteredZero": false,
                "axisColorMode": "text",
                "axisLabel": "",
                "axisPlacement": "auto",
                "barAlignment": 0,
                "barWidthFactor": 0.6,
                "drawStyle": "line",
                "fillOpacity": 10,
                "gradientMode": "opacity",
                "hideFrom": {
                  "legend": false,
                  "tooltip": false,
                  "viz": false
                },
                "insertNulls": false,
                "lineInterpolation": "linear",
                "lineWidth": 2,
                "pointSize": 5,
                "scaleDistribution": {
                  "type": "linear"
                },
                "showPoints": "never",
                "spanNulls": false,
                "stacking": {
                  "group": "A",
                  "mode": "none"
                },
                "thresholdsStyle": {
                  "mode": "off"
                }
              },
              "mappings": [],
              "thresholds": {
                "mode": "absolute",
                "steps": [
                  {
                    "color": "green",
                    "value": 0
                  },
                  {
                    "color": "red",
                    "value": 0.8
                  }
                ]
              },
              "unit": "percentunit"
            },
            "overrides": []
          },
          "gridPos": {
            "h": 9,
            "w": 12,
            "x": 12,
            "y": 22
          },
          "id": 4,
          "options": {
            "legend": {
              "calcs": [],
              "displayMode": "table",
              "placement": "right",
              "showLegend": true,
              "width": 220
            },
            "tooltip": {
              "hideZeros": false,
              "mode": "multi",
              "sort": "none"
            }
          },
          "pluginVersion": "12.1.1",
          "targets": [
            {
              "datasource": {
                "type": "prometheus",
                "uid": "prometheus"
              },
              "editorMode": "code",
              "expr": "1 - (node_memory_MemAvailable_bytes / node_memory_MemTotal_bytes)",
              "instant": false,
              "legendFormat": "{{instance}}",
              "range": true,
              "refId": "A"
            }
          ],
          "title": "Memory Usage",
          "type": "timeseries"
        },
        {
          "datasource": {
            "type": "prometheus",
            "uid": "prometheus"
          },
          "fieldConfig": {
            "defaults": {
              "color": {
                "mode": "palette-classic"
              },
              "custom": {
                "axisBorderShow": false,
                "axisCenteredZero": false,
                "axisColorMode": "text",
                "axisLabel": "",
                "axisPlacement": "auto",
                "barAlignment": 0,
                "barWidthFactor": 0.6,
                "drawStyle": "line",
                "fillOpacity": 10,
                "gradientMode": "opacity",
                "hideFrom": {
                  "legend": false,
                  "tooltip": false,
                  "viz": false
                },
                "insertNulls": false,
                "lineInterpolation": "linear",
                "lineWidth": 2,
                "pointSize": 5,
                "scaleDistribution": {
                  "type": "linear"
                },
                "showPoints": "never",
                "spanNulls": false,
                "stacking": {
                  "group": "A",
                  "mode": "none"
                },
                "thresholdsStyle": {
                  "mode": "off"
                }
              },
              "mappings": [],
              "thresholds": {
                "mode": "absolute",
                "steps": [
                  {
                    "color": "green",
                    "value": 0
                  },
                  {
                    "color": "red",
                    "value": 0.8
                  }
                ]
              },
              "unit": "percentunit"
            },
            "overrides": []
          },
          "gridPos": {
            "h": 9,
            "w": 24,
            "x": 0,
            "y": 31
          },
          "id": 5,
          "options": {
            "legend": {
              "calcs": [],
              "displayMode": "table",
              "placement": "right",
              "showLegend": true,
              "width": 260
            },
            "tooltip": {
              "hideZeros": false,
              "mode": "multi",
              "sort": "none"
            }
          },
          "pluginVersion": "12.1.1",
          "targets": [
            {
              "datasource": {
                "type": "prometheus",
                "uid": "prometheus"
              },
              "editorMode": "code",
              "expr": "1 - ((node_filesystem_avail_bytes{fstype!~\"tmpfs|fuse.lxcfs\"} * on(instance, device, mountpoint) group_left() node_filesystem_readonly{fstype!~\"tmpfs|fuse.lxcfs\"} == 0) / node_filesystem_size_bytes{fstype!~\"tmpfs|fuse.lxcfs\"})",
              "instant": false,
              "legendFormat": "{{instance}} {{mountpoint}}",
              "range": true,
              "refId": "A"
            }
          ],
          "title": "Disk Usage",
          "type": "timeseries"
        }
      ],
      "title": "Resources",
      "type": "row"
    }
  ],
  "preload": false,
  "refresh": "30s",
  "schemaVersion": 41,
  "tags": [
    "app",
    "prometheus"
  ],
  "templating": {
    "list": [
      {
        "current": {
          "text": "95",
          "value": "95"
        },
        "includeAll": false,
        "label": "Percentile",
        "name": "percentile",
        "options": [
          {
            "selected": true,
            "text": "95",
            "value": "95"
          },
          {
            "selected": false,
            "text": "98",
            "value": "98"
          },
          {
            "selected": false,
            "text": "99",
            "value": "99"
          }
        ],
        "query": "95,98,99",
        "type": "custom"
      }
    ]
  },
  "time": {
    "from": "now-6h",
    "to": "now"
  },
  "timepicker": {},
  "timezone": "",
  "title": "App Overview",
  "uid": "app-overview",
  "version": 12
}
